client.py
server.py
mseep_mcp_wikidata-0.1.4.dist-info/licenses/LICENSE
mseep_mcp_wikidata-0.1.4.dist-info/METADATA
mseep_mcp_wikidata-0.1.4.dist-info/WHEEL
mseep_mcp_wikidata-0.1.4.dist-info/top_level.txt
mseep_mcp_wikidata-0.1.4.dist-info/RECORD
